README.txt
setup.cfg
setup.py
connix/__init__.py
connix/__main__.py
connix/connix.py
connix.egg-info/PKG-INFO
connix.egg-info/SOURCES.txt
connix.egg-info/dependency_links.txt
connix.egg-info/top_level.txt