Metadata-Version: 2.1
Name: connix
Version: 1.24
Summary: Connix is a general purpose Python 3.x library that contains a lot of commonly done operations inside of a single package.
Home-page: https://dendory.net
Download-URL: https://pypi.org/project/connix/
Author: Patrick Lambert
Author-email: patrick@dendory.ca
License: MIT
Keywords: connix,util
